[
  {
    "version_code": "ABB",
    "version_name": "",
    "english_name": ""
  },
  {
    "version_code": "ABM",
    "version_name": "",
    "english_name": ""
  },
  {
    "version_code": "ABS",
    "version_name": "",
    "english_name": ""
  },
  {
    "version_code": "ABT",
    "version_name": "",
    "english_name": ""
  },
  {
    "version_code": "ABU",
    "version_name": "",
    "english_name": ""
  },
  {
    "version_code": "AFV",
    "version_name": "",
    "english_name": ""
  },
  {
    "version_code": "AMB",
    "version_name": "",
    "english_name": ""
  },
  {
    "version_code": "ANC",
    "version_name": "",
    "english_name": ""
  },
  {
    "version_code": "ARA",
    "version_name": "",
    "english_name": ""
  },
  {
    "version_code": "ARC",
    "version_name": "",
    "english_name": ""
  },
  {
    "version_code": "ASA",
    "version_name": "",
    "english_name": ""
  },
  {
    "version_code": "ASI",
    "version_name": "",
    "english_name": ""
  },
  {
    "version_code": "BBS",
    "version_name": "",
    "english_name": ""
  },
  {
    "version_code": "BCN",
    "version_name": "",
    "english_name": ""
  },
  {
    "version_code": "BEC",
    "version_name": "",
    "english_name": ""
  },
  {
    "version_code": "BFV",
    "version_name": "",
    "english_name": ""
  },
  {
    "version_code": "BLV",
    "version_name": "",
    "english_name": ""
  },
  {
    "version_code": "BNV",
    "version_name": "",
    "english_name": ""
  },
  {
    "version_code": "BSB",
    "version_name": "",
    "english_name": ""
  },
  {
    "version_code": "BSC",
    "version_name": "",
    "english_name": ""
  },
  {
    "version_code": "BSE",
    "version_name": "",
    "english_name": ""
  },
  {
    "version_code": "BSG",
    "version_name": "",
    "english_name": ""
  },
  {
    "version_code": "BSI",
    "version_name": "",
    "english_name": ""
  },
  {
    "version_code": "BSK",
    "version_name": "",
    "english_name": ""
  },
  {
    "version_code": "BSL",
    "version_name": "",
    "english_name": ""
  },
  {
    "version_code": "BSM",
    "version_name": "",
    "english_name": ""
  },
  {
    "version_code": "BSN",
    "version_name": "",
    "english_name": ""
  },
  {
    "version_code": "BSP",
    "version_name": "",
    "english_name": ""
  },
  {
    "version_code": "BSR",
    "version_name": "",
    "english_name": ""
  },
  {
    "version_code": "BSU",
    "version_name": "",
    "english_name": ""
  },
  {
    "version_code": "BSV",
    "version_name": "",
    "english_name": ""
  },
  {
    "version_code": "BSZ",
    "version_name": "",
    "english_name": ""
  },
  {
    "version_code": "BTT",
    "version_name": "",
    "english_name": ""
  },
  {
    "version_code": "CBS",
    "version_name": "",
    "english_name": ""
  },
  {
    "version_code": "CET",
    "version_name": "",
    "english_name": ""
  },
  {
    "version_code": "COV",
    "version_name": "",
    "english_name": ""
  },
  {
    "version_code": "CRV",
    "version_name": "",
    "english_name": ""
  },
  {
    "version_code": "DRC",
    "version_name": "",
    "english_name": ""
  },
  {
    "version_code": "FAN",
    "version_name": "",
    "english_name": ""
  },
  {
    "version_code": "FBK",
    "version_name": "",
    "english_name": ""
  },
  {
    "version_code": "GIL",
    "version_name": "",
    "english_name": ""
  },
  {
    "version_code": "GNN",
    "version_name": "",
    "english_name": ""
  },
  {
    "version_code": "GUJ",
    "version_name": "",
    "english_name": ""
  },
  {
    "version_code": "HBS",
    "version_name": "",
    "english_name": ""
  },
  {
    "version_code": "HNV",
    "version_name": "",
    "english_name": ""
  },
  {
    "version_code": "HPV",
    "version_name": "",
    "english_name": ""
  },
  {
    "version_code": "ICG",
    "version_name": "",
    "english_name": ""
  },
  {
    "version_code": "ILM",
    "version_name": "",
    "english_name": ""
  },
  {
    "version_code": "KCV",
    "version_name": "",
    "english_name": ""
  },
  {
    "version_code": "KID",
    "version_name": "",
    "english_name": ""
  },
  {
    "version_code": "KSS",
    "version_name": "",
    "english_name": ""
  },
  {
    "version_code": "LAI",
    "version_name": "",
    "english_name": ""
  },
  {
    "version_code": "LBS",
    "version_name": "",
    "english_name": ""
  },
  {
    "version_code": "LSB",
    "version_name": "",
    "english_name": ""
  },
  {
    "version_code": "LVK",
    "version_name": "",
    "english_name": ""
  },
  {
    "version_code": "LVR",
    "version_name": "",
    "english_name": ""
  },
  {
    "version_code": "MBB",
    "version_name": "",
    "english_name": ""
  },
  {
    "version_code": "MBV",
    "version_name": "",
    "english_name": ""
  },
  {
    "version_code": "MHV",
    "version_name": "",
    "english_name": ""
  },
  {
    "version_code": "MJR",
    "version_name": "",
    "english_name": ""
  },
  {
    "version_code": "MLT",
    "version_name": "",
    "english_name": ""
  },
  {
    "version_code": "MOP",
    "version_name": "",
    "english_name": ""
  },
  {
    "version_code": "MVR",
    "version_name": "",
    "english_name": ""
  },
  {
    "version_code": "NBV",
    "version_name": "",
    "english_name": ""
  },
  {
    "version_code": "NDC",
    "version_name": "",
    "english_name": ""
  },
  {
    "version_code": "NIT",
    "version_name": "",
    "english_name": ""
  },
  {
    "version_code": "NRF",
    "version_name": "",
    "english_name": ""
  },
  {
    "version_code": "NRV",
    "version_name": "",
    "english_name": ""
  },
  {
    "version_code": "NTM",
    "version_name": "",
    "english_name": ""
  },
  {
    "version_code": "NTP",
    "version_name": "",
    "english_name": ""
  },
  {
    "version_code": "NVR",
    "version_name": "",
    "english_name": ""
  },
  {
    "version_code": "NVS",
    "version_name": "",
    "english_name": ""
  },
  {
    "version_code": "NVV",
    "version_name": "",
    "english_name": ""
  },
  {
    "version_code": "NZV",
    "version_name": "",
    "english_name": ""
  },
  {
    "version_code": "OJV",
    "version_name": "",
    "english_name": ""
  },
  {
    "version_code": "OVV",
    "version_name": "",
    "english_name": ""
  },
  {
    "version_code": "PBS",
    "version_name": "",
    "english_name": ""
  },
  {
    "version_code": "PBT",
    "version_name": "",
    "english_name": ""
  },
  {
    "version_code": "PIL",
    "version_name": "",
    "english_name": ""
  },
  {
    "version_code": "PMC",
    "version_name": "",
    "english_name": ""
  },
  {
    "version_code": "PNG",
    "version_name": "",
    "english_name": ""
  },
  {
    "version_code": "PRM",
    "version_name": "",
    "english_name": ""
  },
  {
    "version_code": "PVV",
    "version_name": "",
    "english_name": ""
  },
  {
    "version_code": "RBD",
    "version_name": "",
    "english_name": ""
  },
  {
    "version_code": "RBV",
    "version_name": "",
    "english_name": ""
  },
  {
    "version_code": "RDC",
    "version_name": "",
    "english_name": ""
  },
  {
    "version_code": "RGB",
    "version_name": "",
    "english_name": ""
  },
  {
    "version_code": "RNV",
    "version_name": "",
    "english_name": ""
  },
  {
    "version_code": "ROV",
    "version_name": "",
    "english_name": ""
  },
  {
    "version_code": "RVV",
    "version_name": "",
    "english_name": ""
  },
  {
    "version_code": "SAF",
    "version_name": "",
    "english_name": ""
  },
  {
    "version_code": "SBB",
    "version_name": "",
    "english_name": ""
  },
  {
    "version_code": "SBE",
    "version_name": "",
    "english_name": ""
  },
  {
    "version_code": "SBH",
    "version_name": "",
    "english_name": ""
  },
  {
    "version_code": "SBM",
    "version_name": "",
    "english_name": ""
  },
  {
    "version_code": "SBN",
    "version_name": "",
    "english_name": ""
  },
  {
    "version_code": "SBP",
    "version_name": "",
    "english_name": ""
  },
  {
    "version_code": "SBS",
    "version_name": "",
    "english_name": ""
  },
  {
    "version_code": "SBU",
    "version_name": "",
    "english_name": ""
  },
  {
    "version_code": "SIM",
    "version_name": "",
    "english_name": ""
  },
  {
    "version_code": "SSR",
    "version_name": "",
    "english_name": ""
  },
  {
    "version_code": "SVR",
    "version_name": "",
    "english_name": ""
  },
  {
    "version_code": "TMP",
    "version_name": "",
    "english_name": ""
  },
  {
    "version_code": "TPV",
    "version_name": "",
    "english_name": ""
  },
  {
    "version_code": "TTB",
    "version_name": "",
    "english_name": ""
  },
  {
    "version_code": "UBS",
    "version_name": "",
    "english_name": ""
  },
  {
    "version_code": "UFM",
    "version_name": "",
    "english_name": ""
  },
  {
    "version_code": "UNB",
    "version_name": "",
    "english_name": ""
  },
  {
    "version_code": "USA",
    "version_name": "",
    "english_name": ""
  },
  {
    "version_code": "UVR",
    "version_name": "",
    "english_name": ""
  },
  {
    "version_code": "WPS",
    "version_name": "",
    "english_name": ""
  },
  {
    "version_code": "ZIV",
    "version_name": "",
    "english_name": ""
  },
  {
    "version_code": "BDA",
    "version_name": "Biblia de América",
    "english_name": " Biblia de America"
  },
  {
    "version_code": "HLE",
    "version_name": "Hermanos Libres del Ecuador",
    "english_name": " Hermanos Libres del Ecuador"
  },
  {
    "version_code": "L45",
    "version_name": "1545 Luther Bibel",
    "english_name": "1545 Luther Bibel"
  },
  {
    "version_code": "SEV",
    "version_name": "1569 Sagradas Escrituras Version",
    "english_name": "1569 Sagradas Escrituras Version"
  },
  {
    "version_code": "K90",
    "version_name": "1590 Károli Bible",
    "english_name": "1590 Károli Bible"
  },
  {
    "version_code": "PBG",
    "version_name": "1632 Polish Biblia Gdanska",
    "english_name": "1632 Polish Biblia Gdanska"
  },
  {
    "version_code": "S76",
    "version_name": "1876 Synodal Version Bible",
    "english_name": "1876 Synodal Version Bible"
  },
  {
    "version_code": "DBY",
    "version_name": "1885 Darby",
    "english_name": "1885 Darby"
  },
  {
    "version_code": "TAB",
    "version_name": "1905 Ang Dating Biblia",
    "english_name": "1905 Ang Dating Biblia"
  },
  {
    "version_code": "D05",
    "version_name": "1905 Darby Unrevidierte Elberfel",
    "english_name": "1905 Darby Unrevidierte Elberfel"
  },
  {
    "version_code": "LSV",
    "version_name": "1910 Louis Segond",
    "english_name": "1910 Louis Segond"
  },
  {
    "version_code": "L12",
    "version_name": "1912 Luther Bibel",
    "english_name": "1912 Luther Bibel"
  },
  {
    "version_code": "S17",
    "version_name": "1917 Swedish Bible",
    "english_name": "1917 Swedish Bible"
  },
  {
    "version_code": "R27",
    "version_name": "1927 Riveduta Bibbia",
    "english_name": "1927 Riveduta Bibbia"
  },
  {
    "version_code": "NBS",
    "version_name": "1930 Det Norsk Bibelselskap",
    "english_name": "1930 Det Norsk Bibelselskap"
  },
  {
    "version_code": "V34",
    "version_name": "1934 Vietnamese Bible",
    "english_name": "1934 Vietnamese Bible"
  },
  {
    "version_code": "38V",
    "version_name": "1938 Suomennos Version",
    "english_name": "1938 Suomennos Version"
  },
  {
    "version_code": "CJV",
    "version_name": "1955 Colloquial Japanese",
    "english_name": "1955 Colloquial Japanese"
  },
  {
    "version_code": "V67",
    "version_name": "1967 Vellas Version",
    "english_name": "1967 Vellas Version"
  },
  {
    "version_code": "D71",
    "version_name": "1971 Darby Unrevidierte Elberfel",
    "english_name": "1971 Darby Unrevidierte Elberfel"
  },
  {
    "version_code": "NTV",
    "version_name": "1974 New Translation Version",
    "english_name": "1974 New Translation Version"
  },
  {
    "version_code": "SBI",
    "version_name": "2001 Edition",
    "english_name": "2001 Edition"
  },
  {
    "version_code": "RVG",
    "version_name": "2004 Reina Valera Gomez Bible",
    "english_name": "2004 Reina Valera Gomez Bible"
  },
  {
    "version_code": "ATV",
    "version_name": "Aatasara Tairora Version",
    "english_name": "Aatasara Tairora Version"
  },
  {
    "version_code": "AEM",
    "version_name": "AEM",
    "english_name": "AEM"
  },
  {
    "version_code": "AIE",
    "version_name": "AIESE Asociación de Iglesias Evangélicas Shuar",
    "english_name": "AIESE Asociacion de Iglesias Evangelicas Shuar"
  },
  {
    "version_code": "AS3",
    "version_name": "Al Sharif (Iraqi) Version",
    "english_name": "Al Sharif (Iraqi) Version"
  },
  {
    "version_code": "AS2",
    "version_name": "Al Sharif (Sundanese) Version",
    "english_name": "Al Sharif (Sundanese) Version"
  },
  {
    "version_code": "AS1",
    "version_name": "Al Sharif Version",
    "english_name": "Al Sharif Version"
  },
  {
    "version_code": "ABV",
    "version_name": "Albanian Bible Version",
    "english_name": "Albanian Bible Version"
  },
  {
    "version_code": "AVB",
    "version_name": "Alkitab Versi Borneo",
    "english_name": "Alkitab Versi Borneo"
  },
  {
    "version_code": "ACF",
    "version_name": "Almeida Corrigida Fiel",
    "english_name": "Almeida Corrigida Fiel"
  },
  {
    "version_code": "MVA",
    "version_name": "Missão Evangélica da Amazônia",
    "english_name": "Amazon Evangelical Mission"
  },
  {
    "version_code": "AMV",
    "version_name": "Ambulas-Maprik",
    "english_name": "Ambulas-Maprik"
  },
  {
    "version_code": "AWV",
    "version_name": "Ambulas-Wosera-Kamu",
    "english_name": "Ambulas-Wosera-Kamu"
  },
  {
    "version_code": "ASV",
    "version_name": "American Standard Version",
    "english_name": "American Standard Version"
  },
  {
    "version_code": "AND",
    "version_name": "AND",
    "english_name": "AND"
  },
  {
    "version_code": "AOV",
    "version_name": "AOV",
    "english_name": "AOV"
  },
  {
    "version_code": "AKK",
    "version_name": "Archdiocese of Kota Kinabalu",
    "english_name": "Archdiocese of Kota Kinabalu"
  },
  {
    "version_code": "ARV",
    "version_name": "ARV",
    "english_name": "ARV"
  },
  {
    "version_code": "SSI",
    "version_name": "Asian Sahyogi Sanstha India",
    "english_name": "Asian Sahyogi Sanstha India"
  },
  {
    "version_code": "ATB",
    "version_name": "Association Traduire la Bible and La Ligue Biblique",
    "english_name": "Association Traduire la Bible and La Ligue Biblique"
  },
  {
    "version_code": "AVV",
    "version_name": "Audio Visuales para América Latina",
    "english_name": "Audio Visuales para America Latina"
  },
  {
    "version_code": "BEV",
    "version_name": "Basic English Bible 1949/1964",
    "english_name": "Basic English Bible 1949/1964"
  },
  {
    "version_code": "BGC",
    "version_name": "Bharatiya General Conference Mennonite Church",
    "english_name": "Bharatiya General Conference Mennonite Church"
  },
  {
    "version_code": "ABC",
    "version_name": "Bible Society",
    "english_name": "Bible Society"
  },
  {
    "version_code": "IBS",
    "version_name": "Bible Society",
    "english_name": "Bible Society"
  },
  {
    "version_code": "EBS",
    "version_name": "Bible Society of Egypt",
    "english_name": "Bible Society of Egypt"
  },
  {
    "version_code": "BS1",
    "version_name": "Bible Society of Senegal",
    "english_name": "Bible Society of Senegal"
  },
  {
    "version_code": "BST",
    "version_name": "Bible Society of Tanzania",
    "english_name": "Bible Society of Tanzania"
  },
  {
    "version_code": "SBZ",
    "version_name": "Bible Society of the DRC",
    "english_name": "Bible Society of the DRC"
  },
  {
    "version_code": "BSW",
    "version_name": "Bible Society of the West Indies",
    "english_name": "Bible Society of the West Indies"
  },
  {
    "version_code": "BS2",
    "version_name": "Bible Society of Togo",
    "english_name": "Bible Society of Togo"
  },
  {
    "version_code": "BTL",
    "version_name": "Bible Translation and Literacy",
    "english_name": "Bible Translation and Literacy"
  },
  {
    "version_code": "BTA",
    "version_name": "Bible Translation Association",
    "english_name": "Bible Translation Association"
  },
  {
    "version_code": "BIV",
    "version_name": "Bibles International Version",
    "english_name": "Bibles International Version"
  },
  {
    "version_code": "BPV",
    "version_name": "Bikol Popular Version",
    "english_name": "Bikol Popular Version"
  },
  {
    "version_code": "BSA",
    "version_name": "BSA",
    "english_name": "BSA"
  },
  {
    "version_code": "BSS",
    "version_name": "BSS",
    "english_name": "BSS"
  },
  {
    "version_code": "B40",
    "version_name": "Bulgarian Bible 1940",
    "english_name": "Bulgarian Bible 1940"
  },
  {
    "version_code": "CAB",
    "version_name": "CABTAL",
    "english_name": "CABTAL"
  },
  {
    "version_code": "CAT",
    "version_name": "Catholic Version",
    "english_name": "Catholic Version"
  },
  {
    "version_code": "CBV",
    "version_name": "CBV",
    "english_name": "CBV"
  },
  {
    "version_code": "CAR",
    "version_name": "Central African Republic",
    "english_name": "Central African Republic"
  },
  {
    "version_code": "AVA",
    "version_name": "Chatino Lachao - Yolotepec",
    "english_name": "Chatino Lachao - Yolotepec"
  },
  {
    "version_code": "CNV",
    "version_name": "Chinese New Version",
    "english_name": "Chinese New Version"
  },
  {
    "version_code": "CMU",
    "version_name": "CHRISTIAN MISSIONS FOR THE UNREACHED",
    "english_name": "CHRISTIAN MISSIONS FOR THE UNREACHED"
  },
  {
    "version_code": "CLV",
    "version_name": "Common Language Version",
    "english_name": "Common Language Version"
  },
  {
    "version_code": "CEV",
    "version_name": "Contemporary English Version",
    "english_name": "Contemporary English Version"
  },
  {
    "version_code": "CAV",
    "version_name": "Contemporary English Version-AA",
    "english_name": "Contemporary English Version-AA"
  },
  {
    "version_code": "NAN",
    "version_name": "Contemporary English Version-NA",
    "english_name": "Contemporary English Version-NA"
  },
  {
    "version_code": "CWK",
    "version_name": "CWK",
    "english_name": "CWK"
  },
  {
    "version_code": "K13",
    "version_name": "Czech Bible Kralicka (1613)",
    "english_name": "Czech Bible Kralicka (1613)"
  },
  {
    "version_code": "D33",
    "version_name": "Danish Bible 1933",
    "english_name": "Danish Bible 1933"
  },
  {
    "version_code": "DVS",
    "version_name": "Dinh Vinh Sang",
    "english_name": "Dinh Vinh Sang"
  },
  {
    "version_code": "DHH",
    "version_name": "Dios Habla Hoy",
    "english_name": "Dios Habla Hoy"
  },
  {
    "version_code": "C28",
    "version_name": "Dumitru Cornilescu 1928",
    "english_name": "Dumitru Cornilescu 1928"
  },
  {
    "version_code": "DCV",
    "version_name": "Dumitru Cornilescu Version",
    "english_name": "Dumitru Cornilescu Version"
  },
  {
    "version_code": "DSV",
    "version_name": "Dutch Staten Vertaling 1750",
    "english_name": "Dutch Staten Vertaling 1750"
  },
  {
    "version_code": "EAB",
    "version_name": "EAB",
    "english_name": "EAB"
  },
  {
    "version_code": "EST",
    "version_name": "East",
    "english_name": "East"
  },
  {
    "version_code": "EHP",
    "version_name": "Eastern Himalayan Language and Literacy Project",
    "english_name": "Eastern Himalayan Language and Literacy Project"
  },
  {
    "version_code": "ERV",
    "version_name": "Easy to Read Version",
    "english_name": "Easy to Read Version"
  },
  {
    "version_code": "EPT",
    "version_name": "Ecumenical Patriarchal Text",
    "english_name": "Ecumenical Patriarchal Text"
  },
  {
    "version_code": "ELV",
    "version_name": "Elberfelder Bible",
    "english_name": "Elberfelder Bible"
  },
  {
    "version_code": "ESV",
    "version_name": "English Standard Version   ",
    "english_name": "English Standard Version   "
  },
  {
    "version_code": "EKI",
    "version_name": "English Standard Version - KIDZ ",
    "english_name": "English Standard Version - KIDZ "
  },
  {
    "version_code": "EVD",
    "version_name": "English Version for the Deaf",
    "english_name": "English Version for the Deaf"
  },
  {
    "version_code": "EPC",
    "version_name": "EPC",
    "english_name": "EPC"
  },
  {
    "version_code": "EVG",
    "version_name": "EVG",
    "english_name": "EVG"
  },
  {
    "version_code": "JFA",
    "version_name": "Tradução de João Ferreira de Almeida",
    "english_name": "Ferreira de Almeida"
  },
  {
    "version_code": "FIL",
    "version_name": "Filifita",
    "english_name": "Filifita"
  },
  {
    "version_code": "P38",
    "version_name": "Finnish Pyhz Raamatuu 1938",
    "english_name": "Finnish Pyhz Raamatuu 1938"
  },
  {
    "version_code": "FMP",
    "version_name": "FMP",
    "english_name": "FMP"
  },
  {
    "version_code": "FSA",
    "version_name": "Folk&Språk and Swedish Mission Alliance",
    "english_name": "Folk and Sprak and Swedish Mission Alliance"
  },
  {
    "version_code": "FBC",
    "version_name": "Full Bible Content",
    "english_name": "Full Bible Content"
  },
  {
    "version_code": "GDV",
    "version_name": "GDV",
    "english_name": "GDV"
  },
  {
    "version_code": "GID",
    "version_name": "GID",
    "english_name": "GID"
  },
  {
    "version_code": "GBT",
    "version_name": "Global Bible Translators",
    "english_name": "Global Bible Translators"
  },
  {
    "version_code": "GNB",
    "version_name": "Good News",
    "english_name": "Good News"
  },
  {
    "version_code": "GN1",
    "version_name": "Good News (Khaligi) Version",
    "english_name": "Good News (Khaligi) Version"
  },
  {
    "version_code": "GNV",
    "version_name": "Good News Version",
    "english_name": "Good News Version"
  },
  {
    "version_code": "GOV",
    "version_name": "GOV",
    "english_name": "GOV"
  },
  {
    "version_code": "LHG",
    "version_name": "Group Liturgy of the Hours",
    "english_name": "Group Liturgy of the Hours"
  },
  {
    "version_code": "GVR",
    "version_name": "Gustavo Venegas",
    "english_name": "Gustavo Venegas"
  },
  {
    "version_code": "GVA",
    "version_name": "GVA",
    "english_name": "GVA"
  },
  {
    "version_code": "HCV",
    "version_name": "Haitian Creole Bible",
    "english_name": "Haitian Creole Bible"
  },
  {
    "version_code": "HOV",
    "version_name": "Hammond Version",
    "english_name": "Hammond Version"
  },
  {
    "version_code": "HMT",
    "version_name": "Hebrew Modern Text",
    "english_name": "Hebrew Modern Text"
  },
  {
    "version_code": "HMJ",
    "version_name": "Herman Margarete Janzen",
    "english_name": "Herman Margarete Janzen"
  },
  {
    "version_code": "HLA",
    "version_name": "HLA",
    "english_name": "HLA"
  },
  {
    "version_code": "HDV",
    "version_name": "Hmong Daw Version",
    "english_name": "Hmong Daw Version"
  },
  {
    "version_code": "IBV",
    "version_name": "IBV",
    "english_name": "IBV"
  },
  {
    "version_code": "IEM",
    "version_name": "IEM",
    "english_name": "IEM"
  },
  {
    "version_code": "IB1",
    "version_name": "Institute for Bible Translation",
    "english_name": "Institute for Bible Translation"
  },
  {
    "version_code": "IBT",
    "version_name": "Institute for Bible Translation ",
    "english_name": "Institute for Bible Translation "
  },
  {
    "version_code": "EIV",
    "version_name": "Interconfessional Version",
    "english_name": "Interconfessional Version"
  },
  {
    "version_code": "NCA",
    "version_name": "IYO",
    "english_name": "IYO"
  },
  {
    "version_code": "JFV",
    "version_name": "Jesus Film Video",
    "english_name": "Jesus Film Video"
  },
  {
    "version_code": "JFC",
    "version_name": "JFC",
    "english_name": "JFC"
  },
  {
    "version_code": "FAA",
    "version_name": "Joao Ferreira de Almeida Atualiz",
    "english_name": "Joao Ferreira de Almeida Atualiz"
  },
  {
    "version_code": "KTC",
    "version_name": "Kapingamarangi Bible Translation Committee",
    "english_name": "Kapingamarangi Bible Translation Committee"
  },
  {
    "version_code": "KAZ",
    "version_name": "Kazakh",
    "english_name": "Kazakh"
  },
  {
    "version_code": "KJV",
    "version_name": "King James Version",
    "english_name": "King James Version"
  },
  {
    "version_code": "KLA",
    "version_name": "KLA",
    "english_name": "KLA"
  },
  {
    "version_code": "KBV",
    "version_name": "Korean Bible Version",
    "english_name": "Korean Bible Version"
  },
  {
    "version_code": "KWV",
    "version_name": "KWV",
    "english_name": "KWV"
  },
  {
    "version_code": "KYV",
    "version_name": "KYV",
    "english_name": "KYV"
  },
  {
    "version_code": "BLA",
    "version_name": "La Biblia de las Americas",
    "english_name": "La Biblia de las Americas"
  },
  {
    "version_code": "LBV",
    "version_name": "La Casa de la Biblia",
    "english_name": "La Casa de la Biblia"
  },
  {
    "version_code": "LLB",
    "version_name": "La Liga Biblica",
    "english_name": "La Liga Biblica"
  },
  {
    "version_code": "LND",
    "version_name": "La Nova Diodati",
    "english_name": "La Nova Diodati"
  },
  {
    "version_code": "LAR",
    "version_name": "LAR",
    "english_name": "LAR"
  },
  {
    "version_code": "LSM",
    "version_name": "Larry Edward Marhenke & Sonya Louise Eidsvoog de Marhenke, y sus descendientes",
    "english_name": "Larry Edward Marhenke and Sonya Louise Eidsvoog de Marhenke and their descendents"
  },
  {
    "version_code": "LMM",
    "version_name": "Lederer Messianic Ministries",
    "english_name": "Lederer Messianic Ministries"
  },
  {
    "version_code": "LPY",
    "version_name": "LETRA Paraguay",
    "english_name": "LETRA Paraguay"
  },
  {
    "version_code": "LIO",
    "version_name": "Licht im Osten",
    "english_name": "Licht im Osten"
  },
  {
    "version_code": "LBT",
    "version_name": "Lutheran Bible Translators",
    "english_name": "Lutheran Bible Translators"
  },
  {
    "version_code": "LCN",
    "version_name": "Lutheran Church of Nigeria",
    "english_name": "Lutheran Church of Nigeria"
  },
  {
    "version_code": "MUJ",
    "version_name": "Malcolm and Uma Johnson",
    "english_name": "Malcolm and Uma Johnson"
  },
  {
    "version_code": "MEV",
    "version_name": "Missão Evangélica da Amazônia",
    "english_name": "Missao Evangelica da Amazonia"
  },
  {
    "version_code": "MSV",
    "version_name": "Mitla Studios Version",
    "english_name": "Mitla Studios Version"
  },
  {
    "version_code": "M20",
    "version_name": "Modricker Somali Bible 1920 ",
    "english_name": "Modricker Somali Bible 1920 "
  },
  {
    "version_code": "MUB",
    "version_name": "Mongolian Union Bible Society",
    "english_name": "Mongolian Union Bible Society"
  },
  {
    "version_code": "MBS",
    "version_name": "Morocco Bible Society",
    "english_name": "Morocco Bible Society"
  },
  {
    "version_code": "BMR",
    "version_name": "MUINANE",
    "english_name": "MUINANE"
  },
  {
    "version_code": "NLC",
    "version_name": "NALCA",
    "english_name": "NALCA"
  },
  {
    "version_code": "NAS",
    "version_name": "NAS",
    "english_name": "NAS"
  },
  {
    "version_code": "NLT",
    "version_name": "Navarro-Labourdin",
    "english_name": "Navarro-Labourdin"
  },
  {
    "version_code": "NBP",
    "version_name": "NBP",
    "english_name": "NBP"
  },
  {
    "version_code": "NLP",
    "version_name": "Nepali National Language Preservation Institute",
    "english_name": "Nepali National Language Preservation Institute"
  },
  {
    "version_code": "NAB",
    "version_name": "New American Catholic    ",
    "english_name": "New American Catholic    "
  },
  {
    "version_code": "NCV",
    "version_name": "New Covenant Translation",
    "english_name": "New Covenant Translation"
  },
  {
    "version_code": "NEU",
    "version_name": "Neue evangelistische Übersetzung",
    "english_name": "New evangelistic translation"
  },
  {
    "version_code": "NIR",
    "version_name": "New International Reader's Version",
    "english_name": "New International Reader's Version"
  },
  {
    "version_code": "NIV",
    "version_name": "New International Version",
    "english_name": "New International Version"
  },
  {
    "version_code": "NKJ",
    "version_name": "New King James Version",
    "english_name": "New King James Version"
  },
  {
    "version_code": "NLL",
    "version_name": "New Life Literature",
    "english_name": "New Life Literature"
  },
  {
    "version_code": "EMV",
    "version_name": "NEW MILLENIUM VERSION",
    "english_name": "NEW MILLENIUM VERSION"
  },
  {
    "version_code": "NRS",
    "version_name": "New Revised Standard Version ",
    "english_name": "New Revised Standard Version "
  },
  {
    "version_code": "NCL",
    "version_name": "Newar Christian Literature",
    "english_name": "Newar Christian Literature"
  },
  {
    "version_code": "NTT",
    "version_name": "Nggem Translation Team",
    "english_name": "Nggem Translation Team"
  },
  {
    "version_code": "NXB",
    "version_name": "NHA XUAT BAN TON GIAO",
    "english_name": "NHA XUAT BAN TON GIAO"
  },
  {
    "version_code": "NKO",
    "version_name": "Nkonya",
    "english_name": "Nkonya"
  },
  {
    "version_code": "NLV",
    "version_name": "NLV",
    "english_name": "NLV"
  },
  {
    "version_code": "NMV",
    "version_name": "NMV",
    "english_name": "NMV"
  },
  {
    "version_code": "NPG",
    "version_name": "No Penge",
    "english_name": "No Penge"
  },
  {
    "version_code": "TCM",
    "version_name": "North Thailand Christian Mission",
    "english_name": "North Thailand Christian Mission"
  },
  {
    "version_code": "NLH",
    "version_name": "Nova Traducao na Linguagem de Hoy",
    "english_name": "Nova Traducao na Linguagem de Hoy"
  },
  {
    "version_code": "DLH",
    "version_name": "Nueva Biblia Latinoamericana de Hoy",
    "english_name": "Nueva Biblia Latinoamericana de Hoy"
  },
  {
    "version_code": "NVI",
    "version_name": "Nueva Version Internacional",
    "english_name": "Nueva Version Internacional"
  },
  {
    "version_code": "ODV",
    "version_name": "ODV",
    "english_name": "ODV"
  },
  {
    "version_code": "OTS",
    "version_name": "Old Testament Stories",
    "english_name": "Old Testament Stories"
  },
  {
    "version_code": "KOV",
    "version_name": "Old Version",
    "english_name": "Old Version"
  },
  {
    "version_code": "OOV",
    "version_name": "OOV",
    "english_name": "OOV"
  },
  {
    "version_code": "SDV",
    "version_name": "Orthodox-Septuagint Deuterocanonical Version",
    "english_name": "Orthodox-Septuagint Deuterocanonical Version"
  },
  {
    "version_code": "O96",
    "version_name": "Ostervald Version",
    "english_name": "Ostervald Version"
  },
  {
    "version_code": "OMF",
    "version_name": "Overseas Missionary Fellowship",
    "english_name": "Overseas Missionary Fellowship"
  },
  {
    "version_code": "PAK",
    "version_name": "Pakistan",
    "english_name": "Pakistan"
  },
  {
    "version_code": "PDF",
    "version_name": "Parole de Vie",
    "english_name": "Parole de Vie"
  },
  {
    "version_code": "PDV",
    "version_name": "Parole de Vie Version",
    "english_name": "Parole de Vie Version"
  },
  {
    "version_code": "PDC",
    "version_name": "Parole de Vie Version - Canadian",
    "english_name": "Parole de Vie Version - Canadian"
  },
  {
    "version_code": "PDT",
    "version_name": "PDT",
    "english_name": "PDT"
  },
  {
    "version_code": "PBC",
    "version_name": "Peninsula Bible Church",
    "english_name": "Peninsula Bible Church"
  },
  {
    "version_code": "SPV",
    "version_name": "Popular Version",
    "english_name": "Popular Version"
  },
  {
    "version_code": "PDR",
    "version_name": "Presidio de los Reyes",
    "english_name": "Presidio de los Reyes"
  },
  {
    "version_code": "PTB",
    "version_name": "PTB",
    "english_name": "PTB"
  },
  {
    "version_code": "PD1",
    "version_name": "Public Domain Version",
    "english_name": "Public Domain Version"
  },
  {
    "version_code": "QSE",
    "version_name": "QSE",
    "english_name": "QSE"
  },
  {
    "version_code": "QSV",
    "version_name": "QSV",
    "english_name": "QSV"
  },
  {
    "version_code": "RBC",
    "version_name": "Rawang Bible Committee",
    "english_name": "Rawang Bible Committee"
  },
  {
    "version_code": "R95",
    "version_name": "Reina Valera 1995 Version",
    "english_name": "Reina Valera 1995 Version"
  },
  {
    "version_code": "R02",
    "version_name": "Reina-Valera Antigua 1602",
    "english_name": "Reina-Valera Antigua 1602"
  },
  {
    "version_code": "RNT",
    "version_name": "Revideált új fordítású Biblia (2014)",
    "english_name": "Revised Hungarian New Translation (2014)"
  },
  {
    "version_code": "NKV",
    "version_name": "Revised New Korean Standard Version",
    "english_name": "Revised New Korean Standard Version"
  },
  {
    "version_code": "SKV",
    "version_name": "Revised New Korean Standard Version",
    "english_name": "Revised New Korean Standard Version"
  },
  {
    "version_code": "TEV",
    "version_name": "Revised Today's English Version",
    "english_name": "Revised Today's English Version"
  },
  {
    "version_code": "RUV",
    "version_name": "Revised Union Version",
    "english_name": "Revised Union Version"
  },
  {
    "version_code": "REV",
    "version_name": "Revised Version",
    "english_name": "Revised Version"
  },
  {
    "version_code": "RWT",
    "version_name": "Revised West Translation",
    "english_name": "Revised West Translation"
  },
  {
    "version_code": "RCV",
    "version_name": "Roman Catholic Version",
    "english_name": "Roman Catholic Version"
  },
  {
    "version_code": "RAM",
    "version_name": "Romanes Arbeit Marburg",
    "english_name": "Romanes Arbeit Marburg"
  },
  {
    "version_code": "ROB",
    "version_name": "Romanian Orthodox Bible 1936",
    "english_name": "Romanian Orthodox Bible 1936"
  },
  {
    "version_code": "RPV",
    "version_name": "RPV",
    "english_name": "RPV"
  },
  {
    "version_code": "SAV",
    "version_name": "San Antonio",
    "english_name": "San Antonio"
  },
  {
    "version_code": "SJV",
    "version_name": "San Jeronimo",
    "english_name": "San Jeronimo"
  },
  {
    "version_code": "ITV",
    "version_name": "Scripture Translation for Every People",
    "english_name": "Scripture Translation for Every People"
  },
  {
    "version_code": "STP",
    "version_name": "Scripture Translation for Every People",
    "english_name": "Scripture Translation for Every People"
  },
  {
    "version_code": "SHV",
    "version_name": "Sehari-hari",
    "english_name": "Sehari-hari"
  },
  {
    "version_code": "SFV",
    "version_name": "SFV",
    "english_name": "SFV"
  },
  {
    "version_code": "SHL",
    "version_name": "Shellabear Version",
    "english_name": "Shellabear Version"
  },
  {
    "version_code": "SLS",
    "version_name": "Sign Language Stories",
    "english_name": "Sign Language Stories"
  },
  {
    "version_code": "SLV",
    "version_name": "Sign Language Version",
    "english_name": "Sign Language Version"
  },
  {
    "version_code": "SVD",
    "version_name": "Smith and Van Dyke",
    "english_name": "Smith and Van Dyke"
  },
  {
    "version_code": "SBG",
    "version_name": "Sociedad Biblica Guatemala",
    "english_name": "Sociedad Biblica Guatemala"
  },
  {
    "version_code": "SMV",
    "version_name": "Sofia Muller",
    "english_name": "Sofia Muller"
  },
  {
    "version_code": "SFT",
    "version_name": "Spyros Filos Translation",
    "english_name": "Spyros Filos Translation"
  },
  {
    "version_code": "SFB",
    "version_name": "Stiftelsen Svenska Folkbibeln",
    "english_name": "Stiftelsen Svenska Folkbibeln"
  },
  {
    "version_code": "SSF",
    "version_name": "Stiftelsen Svenska Folkbibeln",
    "english_name": "Stiftelsen Svenska Folkbibeln"
  },
  {
    "version_code": "STY",
    "version_name": "Storying",
    "english_name": "Storying"
  },
  {
    "version_code": "SBV",
    "version_name": "Studium Biblicum Version",
    "english_name": "Studium Biblicum Version"
  },
  {
    "version_code": "BLT",
    "version_name": "Tai Dam",
    "english_name": "Tai Dam"
  },
  {
    "version_code": "EPI",
    "version_name": "Tai Dam",
    "english_name": "Tai Dam"
  },
  {
    "version_code": "THV",
    "version_name": "Taiwan Hakka Version",
    "english_name": "Taiwan Hakka Version"
  },
  {
    "version_code": "TCT",
    "version_name": "TCT",
    "english_name": "TCT"
  },
  {
    "version_code": "TBV",
    "version_name": "Terjemahan Baru",
    "english_name": "Terjemahan Baru"
  },
  {
    "version_code": "TSI",
    "version_name": "Terjemahan Sederhana Indonesia",
    "english_name": "Terjemahan Sederhana Indonesia"
  },
  {
    "version_code": "AAA",
    "version_name": "TEST DATA",
    "english_name": "TEST DATA"
  },
  {
    "version_code": "AAQ",
    "version_name": "TEST DATA",
    "english_name": "TEST DATA"
  },
  {
    "version_code": "Z91",
    "version_name": "Test Version 91a",
    "english_name": "Test Version 91a"
  },
  {
    "version_code": "TBS",
    "version_name": "Thailand Bible Society",
    "english_name": "Thailand Bible Society"
  },
  {
    "version_code": "ATT",
    "version_name": "The Azha translation",
    "english_name": "The Azha translation"
  },
  {
    "version_code": "TBL",
    "version_name": "The Bible League",
    "english_name": "The Bible League"
  },
  {
    "version_code": "IME",
    "version_name": "The Holy Injil in Modern English",
    "english_name": "The Holy Injil in Modern English"
  },
  {
    "version_code": "TSC",
    "version_name": "The Seed Company",
    "english_name": "The Seed Company"
  },
  {
    "version_code": "TVI",
    "version_name": "Theovision International",
    "english_name": "Theovision International"
  },
  {
    "version_code": "TJV",
    "version_name": "Timothy Jones",
    "english_name": "Timothy Jones"
  },
  {
    "version_code": "TSV",
    "version_name": "Nganggo Basa Sunda Sadidinten",
    "english_name": "Today's Version"
  },
  {
    "version_code": "TIV",
    "version_name": "Today's Iban Version",
    "english_name": "Todays Iban Version"
  },
  {
    "version_code": "TTV",
    "version_name": "Today's Taiwanese Version",
    "english_name": "Todays Taiwanese Version"
  },
  {
    "version_code": "TTT",
    "version_name": "Translation Trust",
    "english_name": "Translation Trust"
  },
  {
    "version_code": "TRK",
    "version_name": "TRK",
    "english_name": "TRK"
  },
  {
    "version_code": "O30",
    "version_name": "Ukranian Bible 1930",
    "english_name": "Ukranian Bible 1930"
  },
  {
    "version_code": "UTI",
    "version_name": "Union Nacional de Traductores Indigenas A.C.",
    "english_name": "Union Nacional de Traductores Indigenas A.C."
  },
  {
    "version_code": "UN1",
    "version_name": "联盟版",
    "english_name": "Union Version"
  },
  {
    "version_code": "UN2",
    "version_name": "联盟版",
    "english_name": "Union Version"
  },
  {
    "version_code": "UNV",
    "version_name": "Union Version = 和合本",
    "english_name": "Union Version = 和合本"
  },
  {
    "version_code": "O95",
    "version_name": "Urkainian Ohienko   ",
    "english_name": "Urkainian Ohienko   "
  },
  {
    "version_code": "UBG",
    "version_name": "Uwspółcześniona Biblia Gdańska",
    "english_name": "Uwspolczesniona Biblia Gdanska"
  },
  {
    "version_code": "UMK",
    "version_name": "Uyghurche Muqeddes Kitab",
    "english_name": "Uyghurche Muqeddes Kitab"
  },
  {
    "version_code": "VDV",
    "version_name": "Van Dyke Version",
    "english_name": "Van Dyke Version"
  },
  {
    "version_code": "VMV",
    "version_name": "Velberter Mission Version",
    "english_name": "Velberter Mission Version"
  },
  {
    "version_code": "VAA",
    "version_name": "Vicariato Apostolico de Aguarico",
    "english_name": "Vicariato Apostolico de Aguarico"
  },
  {
    "version_code": "VOV",
    "version_name": "Vietnamese Old Version",
    "english_name": "Vietnamese Old Version"
  },
  {
    "version_code": "CVV",
    "version_name": "Vlax",
    "english_name": "Vlax"
  },
  {
    "version_code": "WBV",
    "version_name": "WBV",
    "english_name": "WBV"
  },
  {
    "version_code": "WTD",
    "version_name": "Wedau Topura Version - dialect",
    "english_name": "Wedau Topura Version - dialect"
  },
  {
    "version_code": "WST",
    "version_name": "West   ",
    "english_name": "West   "
  },
  {
    "version_code": "WIN",
    "version_name": "WIN",
    "english_name": "WIN"
  },
  {
    "version_code": "WMV",
    "version_name": "WMV",
    "english_name": "WMV"
  },
  {
    "version_code": "WGM",
    "version_name": "Words of Grace Ministries",
    "english_name": "Words of Grace Ministries"
  },
  {
    "version_code": "WTC",
    "version_name": "World Bible Translation Center",
    "english_name": "World Bible Translation Center"
  },
  {
    "version_code": "WEB",
    "version_name": "World English Bible",
    "english_name": "World English Bible"
  },
  {
    "version_code": "WED",
    "version_name": "World English Bible",
    "english_name": "World English Bible"
  },
  {
    "version_code": "WFW",
    "version_name": "World for World",
    "english_name": "World for World"
  },
  {
    "version_code": "WTV",
    "version_name": "World Team Version",
    "english_name": "World Team Version"
  },
  {
    "version_code": "WOV",
    "version_name": "WOV",
    "english_name": "WOV"
  },
  {
    "version_code": "WPV",
    "version_name": "WPV",
    "english_name": "WPV"
  },
  {
    "version_code": "WRV",
    "version_name": "WRV",
    "english_name": "WRV"
  },
  {
    "version_code": "WSV",
    "version_name": "WSV",
    "english_name": "WSV"
  },
  {
    "version_code": "WYI",
    "version_name": "Wycliffe Bible Translators Inc. ",
    "english_name": "Wycliffe Bible Translators Inc. "
  },
  {
    "version_code": "WB1",
    "version_name": "Wycliffe Bible Translators, Inc.",
    "english_name": "Wycliffe Bible Translators, Inc."
  },
  {
    "version_code": "WBT",
    "version_name": "Wycliffe Bible Translators, Inc.",
    "english_name": "Wycliffe Bible Translators, Inc."
  },
  {
    "version_code": "WSB",
    "version_name": "Wycliffe Suisse, Bienne",
    "english_name": "Wycliffe Suisse, Bienne"
  },
  {
    "version_code": "YSS",
    "version_name": "Yayasan Sumber Sejahtera",
    "english_name": "Yayasan Sumber Sejahtera"
  },
  {
    "version_code": "YYV",
    "version_name": "Yessan-Mayo Yamano Version",
    "english_name": "Yessan-Mayo Yamano Version"
  },
  {
    "version_code": "YWV",
    "version_name": "Yessan-Mayo Yawu",
    "english_name": "Yessan-Mayo Yawu"
  },
  {
    "version_code": "ZZQ",
    "version_name": "Ze Zoo Zersion",
    "english_name": "Ze Zoo Zersion"
  }
]